odoo/addons/coupon_copy_product/README.rst
odoo/addons/coupon_copy_product/__init__.py
odoo/addons/coupon_copy_product/__manifest__.py
odoo/addons/coupon_copy_product/i18n/coupon_copy_product.pot
odoo/addons/coupon_copy_product/i18n/it.po
odoo/addons/coupon_copy_product/models/__init__.py
odoo/addons/coupon_copy_product/models/coupon_reward.py
odoo/addons/coupon_copy_product/readme/CONTRIBUTORS.rst
odoo/addons/coupon_copy_product/readme/DESCRIPTION.rst
odoo/addons/coupon_copy_product/static/description/icon.png
odoo/addons/coupon_copy_product/static/description/index.html
odoo/addons/coupon_copy_product/tests/__init__.py
odoo/addons/coupon_copy_product/tests/test_coupon_reward.py
odoo14_addon_coupon_copy_product-14.0.1.0.1.dev3.dist-info/METADATA
odoo14_addon_coupon_copy_product-14.0.1.0.1.dev3.dist-info/WHEEL
odoo14_addon_coupon_copy_product-14.0.1.0.1.dev3.dist-info/top_level.txt
odoo14_addon_coupon_copy_product-14.0.1.0.1.dev3.dist-info/RECORD
